ssm_neo4j/DFScode.py
ssm_neo4j/DFSedge.py
ssm_neo4j/__init__.py
ssm_neo4j/cql_string.py
ssm_neo4j/gspan_algorithm.py
ssm_neo4j/gspan_tool.py
ssm_neo4j/neo4j_mining_Edge.py
ssm_neo4j/neo4j_mining_History.py
ssm_neo4j/neo4j_mining_tool.py
ssm_neo4j/project_dfs.py
ssm_neo4j-1.0.dist-info/METADATA
ssm_neo4j-1.0.dist-info/WHEEL
ssm_neo4j-1.0.dist-info/top_level.txt
ssm_neo4j-1.0.dist-info/RECORD
